setup.cfg
setup.py
bin/pghost
pghost/__init__.py
pghost/__version__.py
pghost/pghost.py
pghost.egg-info/PKG-INFO
pghost.egg-info/SOURCES.txt
pghost.egg-info/dependency_links.txt
pghost.egg-info/not-zip-safe
pghost.egg-info/top_level.txt