Metadata-Version: 1.1
Name: pghost
Version: 1.0
Summary: Help you to migrate Pelican's posts and tags to Ghost Edit Add topics
Home-page: https://github.com/ken8203/pghost
Author: Jay Chung
Author-email: ken8203@gmail.com
License: Apache2
Download-URL: https://github.com/ken8203/pghost/archive/1.0.tar.gz
Keywords: blog pelican ghost migrate json
Platform: UNKNOWN
